datawire/__init__.py
datawire/cloud/__init__.py
datawire/cloud/identity.py
datawire/utils/__init__.py
datawire/utils/keys.py
datawire/utils/random.py
datawire/utils/state.py
datawire/utils/tests.py
datawire_cloudtools-0.2.6.data/scripts/dwc
datawire_cloudtools-0.2.6.dist-info/DESCRIPTION.rst
datawire_cloudtools-0.2.6.dist-info/METADATA
datawire_cloudtools-0.2.6.dist-info/metadata.json
datawire_cloudtools-0.2.6.dist-info/RECORD
datawire_cloudtools-0.2.6.dist-info/top_level.txt
datawire_cloudtools-0.2.6.dist-info/WHEEL
