Metadata-Version: 2.0
Name: datawire-cloudtools
Version: 0.2.6
Summary: Datawire Cloud Tools
Home-page: http://datawire.io/
Author: Flynn
Author-email: flynn@datawire.io
License: Closed beta. Contact author with requests.
Keywords: datawire cloud tools
Platform: UNKNOWN
Classifier: Development Status :: 4 - Beta
Classifier: Intended Audience :: Developers
Classifier: Natural Language :: English
Classifier: License :: Other/Proprietary License
Classifier: Programming Language :: Python
Classifier: Programming Language :: Python :: 2
Classifier: Programming Language :: Python :: 2.7
Classifier: Programming Language :: Python :: 3
Classifier: Programming Language :: Python :: 3.5
Classifier: Programming Language :: Python :: Implementation :: CPython
Classifier: Programming Language :: Python :: Implementation :: PyPy
Classifier: Topic :: Software Development :: Libraries :: Python Modules
Requires-Dist: requests (==2.9.1)
Requires-Dist: python-jose (==0.5.5)
